<annotation><folder>images</folder><filename>20200308_00737P.jpg</filename><size><width>574</width><height>510</height></size><object><name>knife</name><bndbox><xmin>396</xmin><ymin>179</ymin><xmax>501</xmax><ymax>208</ymax></bndbox></object><object><name>battery</name><bndbox><xmin>348</xmin><ymin>221</ymin><xmax>398</xmax><ymax>272</ymax></bndbox></object><object><name>battery</name><bndbox><xmin>318</xmin><ymin>253</ymin><xmax>387</xmax><ymax>272</ymax></bndbox></object><object><name>scissors</name><bndbox><xmin>319</xmin><ymin>296</ymin><xmax>453</xmax><ymax>396</ymax></bndbox></object><object><name>scissors</name><bndbox><xmin>354</xmin><ymin>323</ymin><xmax>418</xmax><ymax>449</ymax></bndbox></object><object><name>battery</name><bndbox><xmin>124</xmin><ymin>212</ymin><xmax>288</xmax><ymax>266</ymax></bndbox></object><object><name>battery</name><bndbox><xmin>400</xmin><ymin>250</ymin><xmax>507</xmax><ymax>325</ymax></bndbox></object></annotation>