<annotation><folder>images</folder><filename>20200308_02000P.jpg</filename><size><width>519</width><height>239</height></size><object><name>battery</name><bndbox><xmin>190</xmin><ymin>135</ymin><xmax>244</xmax><ymax>144</ymax></bndbox></object><object><name>battery</name><bndbox><xmin>180</xmin><ymin>144</ymin><xmax>236</xmax><ymax>153</ymax></bndbox></object><object><name>battery</name><bndbox><xmin>197</xmin><ymin>176</ymin><xmax>268</xmax><ymax>190</ymax></bndbox></object><object><name>scissors</name><bndbox><xmin>73</xmin><ymin>98</ymin><xmax>141</xmax><ymax>169</ymax></bndbox></object></annotation>