<annotation><folder>images</folder><filename>20200308_00649P.jpg</filename><size><width>1151</width><height>532</height></size><object><name>lighter</name><bndbox><xmin>76</xmin><ymin>165</ymin><xmax>126</xmax><ymax>189</ymax></bndbox></object><object><name>knife</name><bndbox><xmin>939</xmin><ymin>178</ymin><xmax>1059</xmax><ymax>265</ymax></bndbox></object><object><name>battery</name><bndbox><xmin>101</xmin><ymin>218</ymin><xmax>128</xmax><ymax>253</ymax></bndbox></object><object><name>battery</name><bndbox><xmin>117</xmin><ymin>219</ymin><xmax>134</xmax><ymax>248</ymax></bndbox></object><object><name>battery</name><bndbox><xmin>129</xmin><ymin>223</ymin><xmax>146</xmax><ymax>250</ymax></bndbox></object><object><name>scissors</name><bndbox><xmin>823</xmin><ymin>312</ymin><xmax>992</xmax><ymax>362</ymax></bndbox></object><object><name>lighter</name><bndbox><xmin>624</xmin><ymin>187</ymin><xmax>674</xmax><ymax>224</ymax></bndbox></object><object><name>lighter</name><bndbox><xmin>599</xmin><ymin>186</ymin><xmax>648</xmax><ymax>223</ymax></bndbox></object></annotation>