<annotation><folder>images</folder><filename>20200308_01169P.jpg</filename><size><width>533</width><height>604</height></size><object><name>lighter</name><bndbox><xmin>147</xmin><ymin>375</ymin><xmax>294</xmax><ymax>423</ymax></bndbox></object><object><name>lighter</name><bndbox><xmin>409</xmin><ymin>375</ymin><xmax>448</xmax><ymax>438</ymax></bndbox></object><object><name>lighter</name><bndbox><xmin>425</xmin><ymin>373</ymin><xmax>462</xmax><ymax>439</ymax></bndbox></object><object><name>battery</name><bndbox><xmin>73</xmin><ymin>261</ymin><xmax>127</xmax><ymax>347</ymax></bndbox></object><object><name>battery</name><bndbox><xmin>156</xmin><ymin>486</ymin><xmax>320</xmax><ymax>547</ymax></bndbox></object></annotation>