{"dataset_name": "Xray-Pi", "version": 1.2, "license": "Apache 2", "image": {"image_name": "20200308_01879P.jpg", "width": 547, "height": 384}, "annotations": [{"label_name": "lighter", "label_type": "polygon", "points": [[247.857, 144.122], [188.78, 213.586], [181.964, 216.507], [188.78, 224.947], [206.633, 229.491], [238.119, 234.684], [242.339, 228.192], [296.546, 162.299], [296.871, 157.106], [286.808, 148.342]]}, {"label_name": "lighter", "label_type": "polygon", "points": [[296.546, 187.618], [267.333, 221.051], [267.333, 224.622], [278.369, 229.815], [302.389, 233.711], [305.635, 232.737], [332.577, 197.356]]}, {"label_name": "battery", "label_type": "polygon", "points": [[414.375, 187.943], [452.353, 195.084], [450.405, 201.576], [415.349, 194.759]]}, {"label_name": "battery", "label_type": "polygon", "points": [[409.83, 182.424], [408.532, 210.34], [418.919, 210.989], [420.542, 182.749]]}, {"label_name": "battery", "label_type": "polygon", "points": [[439.369, 198.005], [439.369, 212.936], [447.808, 212.936], [450.73, 197.356], [445.211, 197.031]]}, {"label_name": "battery", "label_type": "polygon", "points": [[405.935, 180.477], [396.522, 202.225], [404.962, 202.874], [415.673, 180.477], [409.83, 179.503]]}, {"label_name": "battery", "label_type": "polygon", "points": [[386.135, 195.408], [375.099, 219.428], [373.476, 223.324], [384.187, 224.947], [395.548, 197.68]]}, {"label_name": "battery", "label_type": "polygon", "points": [[377.046, 191.838], [362.439, 219.428], [372.826, 222.025], [387.433, 195.408]]}, {"label_name": "battery", "label_type": "polygon", "points": [[358.22, 219.104], [353.675, 226.57], [396.197, 233.061], [400.093, 226.894]]}, {"label_name": "battery", "label_type": "polygon", "points": [[394.574, 235.658], [403.014, 239.229], [432.552, 220.402], [430.28, 215.533], [425.736, 216.182], [410.155, 225.92]]}, {"label_name": "battery", "label_type": "polygon", "points": [[392.302, 220.727], [399.119, 226.57], [437.421, 210.664], [434.175, 204.822]]}, {"label_name": "battery", "label_type": "polygon", "points": [[395.224, 210.015], [402.04, 216.832], [440.667, 201.251], [437.421, 194.759]]}, {"label_name": "battery", "label_type": "polygon", "points": [[411.129, 158.404], [407.883, 186.969], [420.542, 186.969], [421.516, 158.729]]}]}